automatic_demuxer
